status_report3/__init__.py
status_report3/core.py
status_report3-1.1.2.dist-info/LICENSE
status_report3-1.1.2.dist-info/METADATA
status_report3-1.1.2.dist-info/WHEEL
status_report3-1.1.2.dist-info/top_level.txt
status_report3-1.1.2.dist-info/RECORD
