Metadata-Version: 2.1
Name: status_report3
Version: 1.1.2
Summary: status report
Author: Kowalski
Author-email: kowalski33791@gmail.com
Requires-Python: >=3.6
License-File: LICENSE
